mtx_api/__init__.py
mtx_api/_doc.py
mtx_api/py.typed
mtx_api/settings.py
mtx_api/client/__init__.py
mtx_api/client/_auth_client.py
mtx_api/client/_base_client.py
mtx_api/client/_jurisdiction_client.py
mtx_api/client/_jurisdiction_elements_client.py
mtx_api/client/_location_client.py
mtx_api/client/_mtx_http_client.py
mtx_api/client/_request_client.py
mtx_api/client/_service_client.py
mtx_api/client/_typology_client.py
mtx_api/client/_user_client.py
mtx_api/client/mtx_client.py
mtx_api/models/__init__.py
mtx_api/models/additional_data.py
mtx_api/models/auth.py
mtx_api/models/base.py
mtx_api/models/common.py
mtx_api/models/errors.py
mtx_api/models/jurisdiction.py
mtx_api/models/medias.py
mtx_api/models/request.py
mtx_api/models/request_comment.py
mtx_api/models/request_media.py
mtx_api/models/service.py
mtx_api/models/typology.py
mtx_api_py-0.5.2.dist-info/METADATA
mtx_api_py-0.5.2.dist-info/WHEEL
mtx_api_py-0.5.2.dist-info/licenses/LICENSE.txt
mtx_api_py-0.5.2.dist-info/RECORD
