Metadata-Version: 2.4
Name: mtx-api-py
Version: 0.5.2
Summary: SDK (wrapper) en Python para la API externa de MTX
Project-URL: Repository, https://bitbucket.org/radmas/mtx_api_py
Author-email: Álvaro Martín Rodríguez <alvaro.martin@radmas.com>
License: MIT
License-File: LICENSE.txt
Keywords: api,mtx,sdk
Classifier: Development Status :: 3 - Alpha
Classifier: Intended Audience :: Developers
Classifier: License :: OSI Approved :: MIT License
Classifier: Programming Language :: Python
Classifier: Programming Language :: Python :: 3
Classifier: Programming Language :: Python :: 3 :: Only
Classifier: Programming Language :: Python :: 3.12
Classifier: Topic :: Software Development :: Libraries
Classifier: Typing :: Typed
Requires-Python: >=3.12.0
Requires-Dist: httpx~=0.28.1
Requires-Dist: pydantic-settings~=2.12.0
Requires-Dist: pydantic~=2.12.4
Requires-Dist: pyjwt~=2.10.1
